{
  "id": "HT1886-en-495",
  "number": 495,
  "title": "Jesus Is Passing",
  "author": "J. E. White",
  "composer": "J. E. White",
  "tune": null,
  "meter": null,
  "language": "en",
  "verses": [
    {
      "number": 1,
      "text": "[Copyright protected content - full text not available]"
    }
  ],
  "metadata": {
    "year": 1886,
    "copyright": "Copyrighted 1886 by J. E. White",
    "themes": [
      "salvation",
      "healing",
      "opportunity"
    ],
    "scripture_references": [
      "Matthew 20:30"
    ],
    "tune_source": "J. E. White",
    "original_language": "en",
    "extraction_status": "metadata_only_copyright_protected"
  }
}