{
  "id": "HGPP-en-033",
  "number": 33,
  "title": "The Resurrection",
  "author": "[unclear]",
  "composer": "[unclear]",
  "tune": "[unclear]",
  "meter": "[unclear]",
  "language": "en",
  "verses": [
    {
      "number": 1,
      "text": "And when the last loud trumpet\nShall rend the vaulted skies,\nAnd bid the entomb'd millions\nFrom their cold beds arise,\nOur ransom'd dust, revived,\nBright beauties shall put on,\nAnd soar to the blest mansions\nWhere our Redeemer's gone."
    },
    {
      "number": 2,
      "text": "Our eyes shall then, with rapture,\nThe Saviour's face behold!\nOur feet, no more diverted,\nShall walk the street of gold!\nOur ears shall hear with transport\nThe hosts celestial sing!\nOur tongues shall chant the glory\nOf our immortal King."
    }
  ],
  "metadata": {
    "year": 1849,
    "copyright": "Public Domain",
    "themes": ["resurrection", "trumpet", "glorification", "heavenly mansions", "immortality"],
    "scripture_references": ["1 Thess 4:16-17", "1 Cor 15:51-54", "Rev 21:21"],
    "tune_source": "[needs verification]",
    "original_language": "en",
    "hymnal_context": "Early Seventh-day Adventist movement"
  }
}