{
  "id": "CS1900-en-573",
  "number": 573,
  "title": "HE GIVETH HIS BELOVED SLEEP",
  "author": "F. L. Wiseman",
  "composer": "Frank Gray",
  "tune": null,
  "meter": null,
  "language": "en",
  "verses": [
    {
      "number": 1,
      "text": "\"For so he giveth his beloved sleep.\" - Ps. 127:2.\n\"He giveth his beloved sleep.\" Blessed words of wondrous truth, which tell\nThe sin of weariness and fret, Without them may we doubt; they bring sweet op-por-tuni-ty soul, Je-sus has one cry: sleep!\nThat sickness summons, disease sends, like sweet-est songs shall mark-ed rest sleep-ing."
    }
  ],
  "chorus": {
    "text": "REFRAIN:\nO sooth-ing words, so off for-get; He giveth his be-lov-ed sleep, He giveth his be-lov-ed sleep."
  },
  "metadata": {
    "year": 1900,
    "copyright": null,
    "themes": ["sleep", "rest", "beloved", "peace", "God's gift"],
    "scripture_references": ["Ps. 127:2"],
    "tune_source": "Frank Gray",
    "original_language": "en"
  }
}