{
  "id": "HT1876-en-026",
  "number": 26,
  "title": "",
  "language": "en",
  "verses": [
    {
      "number": 1,
      "text": "HOW holy God's commands !\nHow just his precepts are !\nCome, cast your burdens on the Lord,\nAnd trust his constant care."
    },
    {
      "number": 2,
      "text": "Beneath his watchful eye\nHis saints securely dwell ;\nThat hand which bears all nature up,\nShall guard his children well."
    },
    {
      "number": 3,
      "text": "Why should this anxious load\nPress down your weary mind ?\nHaste to your Heavenly Father's throne,\nAnd sweet refreshment find."
    },
    {
      "number": 4,
      "text": "His goodness stands approved\nThrough each succeeding day ;\nI'll drop my burden at his feet,\nAnd bear a song away."
    }
  ],
  "metadata": {
    "year": 1876,
    "copyright": "Public Domain",
    "publisher": "Seventh-day Adventist Publishing Association",
    "location": "Battle Creek, Michigan",
    "themes": [
      "God's commands",
      "trust",
      "care",
      "burden"
    ],
    "original_language": "en",
    "has_chorus": false,
    "meter": "S. M."
  }
}