{
  "id": "HT1876-en-279",
  "number": 279,
  "title": "Break, break, eternal day",
  "language": "en",
  "verses": [
    {
      "number": 1,
      "text": "Break, break, eternal day, Bid darkness flee away, Pour on our sight, Light from the world of joy, Bliss pure without alloy; Then ne'er shall gloom annoy, All shall be bright."
    },
    {
      "number": 2,
      "text": "Rise, rise, thou glorious sun, Hasten thy race to run; At God's command, Extend thy healing wings, O'er earth's remotest springs, Reign, O thou King of kings, In this dark land."
    },
    {
      "number": 3,
      "text": "Come, come, thou conquering One, Reign thou upon thy throne In glory bright; Then shall the ransomed raise, Unceasing songs of praise, Throughout eternal days, In perfect light."
    }
  ],
  "metadata": {
    "year": 1876,
    "copyright": "Public Domain",
    "publisher": "Seventh-day Adventist Publishing Association",
    "location": "Battle Creek, Michigan",
    "themes": [
      "second coming",
      "light",
      "glory",
      "victory",
      "praise",
      "eternity"
    ],
    "original_language": "en",
    "has_chorus": false,
    "meter": "6s & 4s"
  }
}